xqdata_rq/__init__.py
xqdata_rq/constant.py
xqdata_rq/func.py
xqdata_rq/utils.py
xqdata_rq-0.1.6.dist-info/LICENSE
xqdata_rq-0.1.6.dist-info/METADATA
xqdata_rq-0.1.6.dist-info/WHEEL
xqdata_rq-0.1.6.dist-info/RECORD
