Metadata-Version: 2.1
Name: xqdata-rq
Version: 0.1.6
Summary: 
Author: xuanqi
Author-email: xuan.q@foxmail.com
Requires-Python: >=3.10,<4.0
Classifier: Programming Language :: Python :: 3
Classifier: Programming Language :: Python :: 3.10
Classifier: Programming Language :: Python :: 3.11
Classifier: Programming Language :: Python :: 3.12
Requires-Dist: rqsdk (>=1.5.14,<2.0.0)
Requires-Dist: xqdata (>=0.1.0,<0.2.0)
